{"commitInfo":{"timestamp":1730407664170,"operation":"WRITE","operationParameters":{"mode":"Overwrite","partitionBy":"[]"},"isolationLevel":"Serializable","isBlindAppend":false,"operationMetrics":{"numFiles":"12","numOutputRows":"193536","numOutputBytes":"159233"},"engineInfo":"Apache-Spark/3.4.0 Delta-Lake/2.4.0","txnId":"0774846b-ef35-4fe5-ae73-c63416e44c1f"}}
{"protocol":{"minReaderVersion":1,"minWriterVersion":2}}
{"metaData":{"id":"cd792008-16b1-418a-8e6e-17b46c44a3ff","format":{"provider":"parquet","options":{}},"schemaString":"{\"type\":\"struct\",\"fields\":[{\"name\":\"production_type\",\"type\":\"string\",\"nullable\":true,\"metadata\":{}},{\"name\":\"timestamp\",\"type\":\"timestamp\",\"nullable\":true,\"metadata\":{}},{\"name\":\"value\",\"type\":\"double\",\"nullable\":true,\"metadata\":{}}]}","partitionColumns":[],"configuration":{},"createdTime":1730407659191}}
{"add":{"path":"part-00000-83e8aa0c-9045-4ccf-9715-8f05e992a60d-c000.snappy.parquet","partitionValues":{},"size":13161,"modificationTime":1730407662594,"dataChange":true,"stats":"{\"numRecords\":15360,\"minValues\":{\"production_type\":\"Biomass\",\"timestamp\":\"2023-12-30T23:00:00.000Z\",\"value\":-11684.8},\"maxValues\":{\"production_type\":\"Wind onshore\",\"timestamp\":\"2023-12-31T00:45:00.000Z\",\"value\":53096.3},\"nullCount\":{\"production_type\":0,\"timestamp\":0,\"value\":768}}"}}
{"add":{"path":"part-00001-9c743b8f-2e1f-46b0-9f04-33ce56d42c22-c000.snappy.parquet","partitionValues":{},"size":13306,"modificationTime":1730407662593,"dataChange":true,"stats":"{\"numRecords\":16384,\"minValues\":{\"production_type\":\"Biomass\",\"timestamp\":\"2023-12-31T00:45:00.000Z\",\"value\":-11684.8},\"maxValues\":{\"production_type\":\"Wind onshore\",\"timestamp\":\"2023-12-31T02:45:00.000Z\",\"value\":53096.3},\"nullCount\":{\"production_type\":0,\"timestamp\":0,\"value\":768}}"}}
{"add":{"path":"part-00002-88b4f34b-0073-49c3-bd8c-85623ddd8efb-c000.snappy.parquet","partitionValues":{},"size":13426,"modificationTime":1730407662594,"dataChange":true,"stats":"{\"numRecords\":16384,\"minValues\":{\"production_type\":\"Biomass\",\"timestamp\":\"2023-12-31T02:45:00.000Z\",\"value\":-11684.8},\"maxValues\":{\"production_type\":\"Wind onshore\",\"timestamp\":\"2023-12-31T04:45:00.000Z\",\"value\":53096.3},\"nullCount\":{\"production_type\":0,\"timestamp\":0,\"value\":768}}"}}
{"add":{"path":"part-00003-803d154b-3228-460c-a191-67f34ec631cb-c000.snappy.parquet","partitionValues":{},"size":13183,"modificationTime":1730407662594,"dataChange":true,"stats":"{\"numRecords\":16384,\"minValues\":{\"production_type\":\"Biomass\",\"timestamp\":\"2023-12-31T04:45:00.000Z\",\"value\":-11684.8},\"maxValues\":{\"production_type\":\"Wind onshore\",\"timestamp\":\"2023-12-31T06:45:00.000Z\",\"value\":53096.3},\"nullCount\":{\"production_type\":0,\"timestamp\":0,\"value\":768}}"}}
{"add":{"path":"part-00004-ad1a3b30-6cbb-4a57-8a01-ff11a5d4796e-c000.snappy.parquet","partitionValues":{},"size":13163,"modificationTime":1730407662594,"dataChange":true,"stats":"{\"numRecords\":15360,\"minValues\":{\"production_type\":\"Biomass\",\"timestamp\":\"2023-12-31T07:00:00.000Z\",\"value\":-11684.8},\"maxValues\":{\"production_type\":\"Wind onshore\",\"timestamp\":\"2023-12-31T08:45:00.000Z\",\"value\":53096.3},\"nullCount\":{\"production_type\":0,\"timestamp\":0,\"value\":768}}"}}
{"add":{"path":"part-00005-d5e103e3-2fc4-42f9-b840-5d9b7d51ef7e-c000.snappy.parquet","partitionValues":{},"size":13308,"modificationTime":1730407662593,"dataChange":true,"stats":"{\"numRecords\":16384,\"minValues\":{\"production_type\":\"Biomass\",\"timestamp\":\"2023-12-31T08:45:00.000Z\",\"value\":-11684.8},\"maxValues\":{\"production_type\":\"Wind onshore\",\"timestamp\":\"2023-12-31T10:45:00.000Z\",\"value\":53096.3},\"nullCount\":{\"production_type\":0,\"timestamp\":0,\"value\":768}}"}}
{"add":{"path":"part-00006-b4b754f1-282b-45b6-a43b-429953317159-c000.snappy.parquet","partitionValues":{},"size":13426,"modificationTime":1730407662593,"dataChange":true,"stats":"{\"numRecords\":16384,\"minValues\":{\"production_type\":\"Biomass\",\"timestamp\":\"2023-12-31T10:45:00.000Z\",\"value\":-11684.8},\"maxValues\":{\"production_type\":\"Wind onshore\",\"timestamp\":\"2023-12-31T12:45:00.000Z\",\"value\":53096.3},\"nullCount\":{\"production_type\":0,\"timestamp\":0,\"value\":768}}"}}
{"add":{"path":"part-00007-d1d2a827-0dbe-4e27-970a-13e851ad7f88-c000.snappy.parquet","partitionValues":{},"size":13183,"modificationTime":1730407662594,"dataChange":true,"stats":"{\"numRecords\":16384,\"minValues\":{\"production_type\":\"Biomass\",\"timestamp\":\"2023-12-31T12:45:00.000Z\",\"value\":-11684.8},\"maxValues\":{\"production_type\":\"Wind onshore\",\"timestamp\":\"2023-12-31T14:45:00.000Z\",\"value\":53096.3},\"nullCount\":{\"production_type\":0,\"timestamp\":0,\"value\":768}}"}}
{"add":{"path":"part-00008-d4bf56ab-c9d7-4e96-8dde-732701ae6130-c000.snappy.parquet","partitionValues":{},"size":13162,"modificationTime":1730407662594,"dataChange":true,"stats":"{\"numRecords\":15360,\"minValues\":{\"production_type\":\"Biomass\",\"timestamp\":\"2023-12-31T15:00:00.000Z\",\"value\":-11684.8},\"maxValues\":{\"production_type\":\"Wind onshore\",\"timestamp\":\"2023-12-31T16:45:00.000Z\",\"value\":53096.3},\"nullCount\":{\"production_type\":0,\"timestamp\":0,\"value\":768}}"}}
{"add":{"path":"part-00009-a9deb63e-4bf5-45a2-9f8d-a8583d5a0563-c000.snappy.parquet","partitionValues":{},"size":13306,"modificationTime":1730407662594,"dataChange":true,"stats":"{\"numRecords\":16384,\"minValues\":{\"production_type\":\"Biomass\",\"timestamp\":\"2023-12-31T16:45:00.000Z\",\"value\":-11684.8},\"maxValues\":{\"production_type\":\"Wind onshore\",\"timestamp\":\"2023-12-31T18:45:00.000Z\",\"value\":53096.3},\"nullCount\":{\"production_type\":0,\"timestamp\":0,\"value\":768}}"}}
{"add":{"path":"part-00010-cb989f6a-f8b9-4f14-a5c6-fdb3bef924b7-c000.snappy.parquet","partitionValues":{},"size":13427,"modificationTime":1730407662593,"dataChange":true,"stats":"{\"numRecords\":16384,\"minValues\":{\"production_type\":\"Biomass\",\"timestamp\":\"2023-12-31T18:45:00.000Z\",\"value\":-11684.8},\"maxValues\":{\"production_type\":\"Wind onshore\",\"timestamp\":\"2023-12-31T20:45:00.000Z\",\"value\":53096.3},\"nullCount\":{\"production_type\":0,\"timestamp\":0,\"value\":768}}"}}
{"add":{"path":"part-00011-d8781024-152e-4cc5-b7f1-b4847ebcc43a-c000.snappy.parquet","partitionValues":{},"size":13182,"modificationTime":1730407662594,"dataChange":true,"stats":"{\"numRecords\":16384,\"minValues\":{\"production_type\":\"Biomass\",\"timestamp\":\"2023-12-31T20:45:00.000Z\",\"value\":-11684.8},\"maxValues\":{\"production_type\":\"Wind onshore\",\"timestamp\":\"2023-12-31T22:45:00.000Z\",\"value\":53096.3},\"nullCount\":{\"production_type\":0,\"timestamp\":0,\"value\":768}}"}}
